{
  "source_url": "https://afltables.com/afl/stats/games/2025/192020250504.html",
  "teams": [
    {
      "game_id": "192020250504",
      "season": 2025,
      "game_number": 72,
      "round_label": "9",
      "match_date": "Sun, 4-May-2025 7:20 PM",
      "venue": "Gabba",
      "attendance": 33612,
      "source_url": "https://afltables.com/afl/stats/games/2025/192020250504.html",
      "team": "Brisbane Lions",
      "opponent": "Gold Coast Suns",
      "team_side": "team_a",
      "result": "win",
      "points_for": 66,
      "points_against": 49,
      "margin": 17,
      "goals": 9,
      "behinds": 12,
      "scoring_shots": 21,
      "goal_accuracy": 0.4286,
      "opponent_goals": 7,
      "opponent_behinds": 7,
      "opponent_scoring_shots": 14,
      "opponent_goal_accuracy": 0.5,
      "shot_diff": 7,
      "accuracy_diff": -0.0714,
      "kicks": 249,
      "marks": 108,
      "handballs": 124,
      "disposals": 373,
      "hitouts": 39,
      "tackles": 67,
      "rebound_50s": 33,
      "inside_50s": 56,
      "clearances": 47,
      "clangers": 55,
      "frees_for": 24,
      "frees_against": 21,
      "contested_possessions": 147,
      "uncontested_possessions": 217,
      "contested_marks": 8,
      "marks_inside_50": 8,
      "one_percenters": 55,
      "bounces": 5,
      "goal_assists": 5,
      "inside_50_diff": 16,
      "clearance_diff": 19,
      "contested_possession_diff": 22,
      "marks_inside_50_diff": 4,
      "forward_efficiency": 0.375,
      "opponent_forward_efficiency": 0.35,
      "forward_efficiency_diff": 0.025,
      "unlucky_loss_score": 0,
      "unlucky_loss_flag": 0
    },
    {
      "game_id": "192020250504",
      "season": 2025,
      "game_number": 72,
      "round_label": "9",
      "match_date": "Sun, 4-May-2025 7:20 PM",
      "venue": "Gabba",
      "attendance": 33612,
      "source_url": "https://afltables.com/afl/stats/games/2025/192020250504.html",
      "team": "Gold Coast Suns",
      "opponent": "Brisbane Lions",
      "team_side": "team_b",
      "result": "loss",
      "points_for": 49,
      "points_against": 66,
      "margin": -17,
      "goals": 7,
      "behinds": 7,
      "scoring_shots": 14,
      "goal_accuracy": 0.5,
      "opponent_goals": 9,
      "opponent_behinds": 12,
      "opponent_scoring_shots": 21,
      "opponent_goal_accuracy": 0.4286,
      "shot_diff": -7,
      "accuracy_diff": 0.0714,
      "kicks": 177,
      "marks": 71,
      "handballs": 152,
      "disposals": 329,
      "hitouts": 51,
      "tackles": 52,
      "rebound_50s": 47,
      "inside_50s": 40,
      "clearances": 28,
      "clangers": 55,
      "frees_for": 21,
      "frees_against": 24,
      "contested_possessions": 125,
      "uncontested_possessions": 201,
      "contested_marks": 9,
      "marks_inside_50": 4,
      "one_percenters": 58,
      "bounces": 3,
      "goal_assists": 2,
      "inside_50_diff": -16,
      "clearance_diff": -19,
      "contested_possession_diff": -22,
      "marks_inside_50_diff": -4,
      "forward_efficiency": 0.35,
      "opponent_forward_efficiency": 0.375,
      "forward_efficiency_diff": -0.025,
      "unlucky_loss_score": 1,
      "unlucky_loss_flag": 0
    }
  ]
}