{
  "source_url": "https://afltables.com/afl/stats/games/2024/031920240907.html",
  "teams": [
    {
      "game_id": "031920240907",
      "season": 2024,
      "game_number": 211,
      "round_label": "Elimination Final",
      "match_date": "Sat, 7-Sep-2024 7:30 PM",
      "venue": "Gabba",
      "attendance": 35660,
      "source_url": "https://afltables.com/afl/stats/games/2024/031920240907.html",
      "team": "Brisbane Lions",
      "opponent": "Carlton Blues",
      "team_side": "team_a",
      "result": "win",
      "points_for": 99,
      "points_against": 71,
      "margin": 28,
      "goals": 14,
      "behinds": 15,
      "scoring_shots": 29,
      "goal_accuracy": 0.4828,
      "opponent_goals": 11,
      "opponent_behinds": 5,
      "opponent_scoring_shots": 16,
      "opponent_goal_accuracy": 0.6875,
      "shot_diff": 13,
      "accuracy_diff": -0.2047,
      "kicks": 213,
      "marks": 100,
      "handballs": 117,
      "disposals": 330,
      "hitouts": 32,
      "tackles": 65,
      "rebound_50s": 44,
      "inside_50s": 56,
      "clearances": 37,
      "clangers": 56,
      "frees_for": 15,
      "frees_against": 13,
      "contested_possessions": 124,
      "uncontested_possessions": 200,
      "contested_marks": 18,
      "marks_inside_50": 20,
      "one_percenters": 39,
      "bounces": 6,
      "goal_assists": 9,
      "inside_50_diff": 0,
      "clearance_diff": 2,
      "contested_possession_diff": -6,
      "marks_inside_50_diff": 10,
      "forward_efficiency": 0.5179,
      "opponent_forward_efficiency": 0.2857,
      "forward_efficiency_diff": 0.2322,
      "unlucky_loss_score": 0,
      "unlucky_loss_flag": 0
    },
    {
      "game_id": "031920240907",
      "season": 2024,
      "game_number": 211,
      "round_label": "Elimination Final",
      "match_date": "Sat, 7-Sep-2024 7:30 PM",
      "venue": "Gabba",
      "attendance": 35660,
      "source_url": "https://afltables.com/afl/stats/games/2024/031920240907.html",
      "team": "Carlton Blues",
      "opponent": "Brisbane Lions",
      "team_side": "team_b",
      "result": "loss",
      "points_for": 71,
      "points_against": 99,
      "margin": -28,
      "goals": 11,
      "behinds": 5,
      "scoring_shots": 16,
      "goal_accuracy": 0.6875,
      "opponent_goals": 14,
      "opponent_behinds": 15,
      "opponent_scoring_shots": 29,
      "opponent_goal_accuracy": 0.4828,
      "shot_diff": -13,
      "accuracy_diff": 0.2047,
      "kicks": 200,
      "marks": 85,
      "handballs": 154,
      "disposals": 354,
      "hitouts": 30,
      "tackles": 42,
      "rebound_50s": 41,
      "inside_50s": 56,
      "clearances": 35,
      "clangers": 61,
      "frees_for": 14,
      "frees_against": 15,
      "contested_possessions": 130,
      "uncontested_possessions": 217,
      "contested_marks": 13,
      "marks_inside_50": 10,
      "one_percenters": 24,
      "bounces": 5,
      "goal_assists": 10,
      "inside_50_diff": 0,
      "clearance_diff": -2,
      "contested_possession_diff": 6,
      "marks_inside_50_diff": -10,
      "forward_efficiency": 0.2857,
      "opponent_forward_efficiency": 0.5179,
      "forward_efficiency_diff": -0.2322,
      "unlucky_loss_score": 3,
      "unlucky_loss_flag": 0
    }
  ]
}