{
  "source_url": "https://afltables.com/afl/stats/games/2024/072020240324.html",
  "teams": [
    {
      "game_id": "072020240324",
      "season": 2024,
      "game_number": 19,
      "round_label": "3",
      "match_date": "Sun, 24-Mar-2024 1:00 PM (12:00 PM)",
      "venue": "Eureka Stadium",
      "attendance": 9752,
      "source_url": "https://afltables.com/afl/stats/games/2024/072020240324.html",
      "team": "Western Bulldogs",
      "opponent": "Gold Coast Suns",
      "team_side": "team_a",
      "result": "win",
      "points_for": 115,
      "points_against": 67,
      "margin": 48,
      "goals": 18,
      "behinds": 7,
      "scoring_shots": 25,
      "goal_accuracy": 0.72,
      "opponent_goals": 10,
      "opponent_behinds": 7,
      "opponent_scoring_shots": 17,
      "opponent_goal_accuracy": 0.5882,
      "shot_diff": 8,
      "accuracy_diff": 0.1318,
      "kicks": 222,
      "marks": 110,
      "handballs": 160,
      "disposals": 382,
      "hitouts": 37,
      "tackles": 65,
      "rebound_50s": 42,
      "inside_50s": 56,
      "clearances": 42,
      "clangers": 68,
      "frees_for": 20,
      "frees_against": 28,
      "contested_possessions": 143,
      "uncontested_possessions": 243,
      "contested_marks": 16,
      "marks_inside_50": 14,
      "one_percenters": 40,
      "bounces": 10,
      "goal_assists": 10,
      "inside_50_diff": 4,
      "clearance_diff": 11,
      "contested_possession_diff": 5,
      "marks_inside_50_diff": 6,
      "forward_efficiency": 0.4464,
      "opponent_forward_efficiency": 0.3269,
      "forward_efficiency_diff": 0.1195,
      "unlucky_loss_score": 0,
      "unlucky_loss_flag": 0
    },
    {
      "game_id": "072020240324",
      "season": 2024,
      "game_number": 19,
      "round_label": "3",
      "match_date": "Sun, 24-Mar-2024 1:00 PM (12:00 PM)",
      "venue": "Eureka Stadium",
      "attendance": 9752,
      "source_url": "https://afltables.com/afl/stats/games/2024/072020240324.html",
      "team": "Gold Coast Suns",
      "opponent": "Western Bulldogs",
      "team_side": "team_b",
      "result": "loss",
      "points_for": 67,
      "points_against": 115,
      "margin": -48,
      "goals": 10,
      "behinds": 7,
      "scoring_shots": 17,
      "goal_accuracy": 0.5882,
      "opponent_goals": 18,
      "opponent_behinds": 7,
      "opponent_scoring_shots": 25,
      "opponent_goal_accuracy": 0.72,
      "shot_diff": -8,
      "accuracy_diff": -0.1318,
      "kicks": 197,
      "marks": 76,
      "handballs": 136,
      "disposals": 333,
      "hitouts": 44,
      "tackles": 58,
      "rebound_50s": 37,
      "inside_50s": 52,
      "clearances": 31,
      "clangers": 55,
      "frees_for": 28,
      "frees_against": 20,
      "contested_possessions": 138,
      "uncontested_possessions": 191,
      "contested_marks": 7,
      "marks_inside_50": 8,
      "one_percenters": 40,
      "bounces": 2,
      "goal_assists": 6,
      "inside_50_diff": -4,
      "clearance_diff": -11,
      "contested_possession_diff": -5,
      "marks_inside_50_diff": -6,
      "forward_efficiency": 0.3269,
      "opponent_forward_efficiency": 0.4464,
      "forward_efficiency_diff": -0.1195,
      "unlucky_loss_score": 7,
      "unlucky_loss_flag": 0
    }
  ]
}