{
  "source_url": "https://afltables.com/afl/stats/games/2024/091820240824.html",
  "teams": [
    {
      "game_id": "091820240824",
      "season": 2024,
      "game_number": 201,
      "round_label": "25",
      "match_date": "Sat, 24-Aug-2024 1:45 PM",
      "venue": "Kardinia Park",
      "attendance": 32545,
      "source_url": "https://afltables.com/afl/stats/games/2024/091820240824.html",
      "team": "Geelong Cats",
      "opponent": "West Coast Eagles",
      "team_side": "team_a",
      "result": "win",
      "points_for": 168,
      "points_against": 75,
      "margin": 93,
      "goals": 26,
      "behinds": 12,
      "scoring_shots": 38,
      "goal_accuracy": 0.6842,
      "opponent_goals": 11,
      "opponent_behinds": 9,
      "opponent_scoring_shots": 20,
      "opponent_goal_accuracy": 0.55,
      "shot_diff": 18,
      "accuracy_diff": 0.1342,
      "kicks": 234,
      "marks": 117,
      "handballs": 163,
      "disposals": 397,
      "hitouts": 42,
      "tackles": 51,
      "rebound_50s": 42,
      "inside_50s": 60,
      "clearances": 44,
      "clangers": 38,
      "frees_for": 27,
      "frees_against": 9,
      "contested_possessions": 118,
      "uncontested_possessions": 263,
      "contested_marks": 11,
      "marks_inside_50": 27,
      "one_percenters": 42,
      "bounces": 16,
      "goal_assists": 20,
      "inside_50_diff": 6,
      "clearance_diff": 4,
      "contested_possession_diff": 0,
      "marks_inside_50_diff": 16,
      "forward_efficiency": 0.6333,
      "opponent_forward_efficiency": 0.3704,
      "forward_efficiency_diff": 0.2629,
      "unlucky_loss_score": 0,
      "unlucky_loss_flag": 0
    },
    {
      "game_id": "091820240824",
      "season": 2024,
      "game_number": 201,
      "round_label": "25",
      "match_date": "Sat, 24-Aug-2024 1:45 PM",
      "venue": "Kardinia Park",
      "attendance": 32545,
      "source_url": "https://afltables.com/afl/stats/games/2024/091820240824.html",
      "team": "West Coast Eagles",
      "opponent": "Geelong Cats",
      "team_side": "team_b",
      "result": "loss",
      "points_for": 75,
      "points_against": 168,
      "margin": -93,
      "goals": 11,
      "behinds": 9,
      "scoring_shots": 20,
      "goal_accuracy": 0.55,
      "opponent_goals": 26,
      "opponent_behinds": 12,
      "opponent_scoring_shots": 38,
      "opponent_goal_accuracy": 0.6842,
      "shot_diff": -18,
      "accuracy_diff": -0.1342,
      "kicks": 183,
      "marks": 78,
      "handballs": 113,
      "disposals": 296,
      "hitouts": 38,
      "tackles": 49,
      "rebound_50s": 33,
      "inside_50s": 54,
      "clearances": 40,
      "clangers": 49,
      "frees_for": 9,
      "frees_against": 27,
      "contested_possessions": 118,
      "uncontested_possessions": 174,
      "contested_marks": 11,
      "marks_inside_50": 11,
      "one_percenters": 29,
      "bounces": 7,
      "goal_assists": 9,
      "inside_50_diff": -6,
      "clearance_diff": -4,
      "contested_possession_diff": 0,
      "marks_inside_50_diff": -16,
      "forward_efficiency": 0.3704,
      "opponent_forward_efficiency": 0.6333,
      "forward_efficiency_diff": -0.2629,
      "unlucky_loss_score": 7,
      "unlucky_loss_flag": 0
    }
  ]
}