{
  "source_url": "https://afltables.com/afl/stats/games/2024/132020240714.html",
  "teams": [
    {
      "game_id": "132020240714",
      "season": 2024,
      "game_number": 151,
      "round_label": "19",
      "match_date": "Sun, 14-Jul-2024 1:10 PM",
      "venue": "Carrara",
      "attendance": 14526,
      "source_url": "https://afltables.com/afl/stats/games/2024/132020240714.html",
      "team": "Gold Coast Suns",
      "opponent": "Port Adelaide Power",
      "team_side": "team_a",
      "result": "win",
      "points_for": 96,
      "points_against": 82,
      "margin": 14,
      "goals": 14,
      "behinds": 12,
      "scoring_shots": 26,
      "goal_accuracy": 0.5385,
      "opponent_goals": 12,
      "opponent_behinds": 10,
      "opponent_scoring_shots": 22,
      "opponent_goal_accuracy": 0.5455,
      "shot_diff": 4,
      "accuracy_diff": -0.007,
      "kicks": 194,
      "marks": 88,
      "handballs": 123,
      "disposals": 317,
      "hitouts": 30,
      "tackles": 66,
      "rebound_50s": 41,
      "inside_50s": 60,
      "clearances": 36,
      "clangers": 57,
      "frees_for": 23,
      "frees_against": 17,
      "contested_possessions": 120,
      "uncontested_possessions": 199,
      "contested_marks": 10,
      "marks_inside_50": 12,
      "one_percenters": 44,
      "bounces": 10,
      "goal_assists": 8,
      "inside_50_diff": 6,
      "clearance_diff": 10,
      "contested_possession_diff": -5,
      "marks_inside_50_diff": 1,
      "forward_efficiency": 0.4333,
      "opponent_forward_efficiency": 0.4074,
      "forward_efficiency_diff": 0.0259,
      "unlucky_loss_score": 0,
      "unlucky_loss_flag": 0
    },
    {
      "game_id": "132020240714",
      "season": 2024,
      "game_number": 151,
      "round_label": "19",
      "match_date": "Sun, 14-Jul-2024 1:10 PM",
      "venue": "Carrara",
      "attendance": 14526,
      "source_url": "https://afltables.com/afl/stats/games/2024/132020240714.html",
      "team": "Port Adelaide Power",
      "opponent": "Gold Coast Suns",
      "team_side": "team_b",
      "result": "loss",
      "points_for": 82,
      "points_against": 96,
      "margin": -14,
      "goals": 12,
      "behinds": 10,
      "scoring_shots": 22,
      "goal_accuracy": 0.5455,
      "opponent_goals": 14,
      "opponent_behinds": 12,
      "opponent_scoring_shots": 26,
      "opponent_goal_accuracy": 0.5385,
      "shot_diff": -4,
      "accuracy_diff": 0.007,
      "kicks": 235,
      "marks": 134,
      "handballs": 148,
      "disposals": 383,
      "hitouts": 38,
      "tackles": 61,
      "rebound_50s": 45,
      "inside_50s": 54,
      "clearances": 26,
      "clangers": 55,
      "frees_for": 17,
      "frees_against": 22,
      "contested_possessions": 125,
      "uncontested_possessions": 255,
      "contested_marks": 14,
      "marks_inside_50": 11,
      "one_percenters": 34,
      "bounces": 7,
      "goal_assists": 10,
      "inside_50_diff": -6,
      "clearance_diff": -10,
      "contested_possession_diff": 5,
      "marks_inside_50_diff": -1,
      "forward_efficiency": 0.4074,
      "opponent_forward_efficiency": 0.4333,
      "forward_efficiency_diff": -0.0259,
      "unlucky_loss_score": 1,
      "unlucky_loss_flag": 0
    }
  ]
}